chatmux/__init__.py
chatmux/convert.py
chatmux/openai.py
chatmux-0.1.5.dist-info/licenses/LICENSE
chatmux-0.1.5.dist-info/METADATA
chatmux-0.1.5.dist-info/WHEEL
chatmux-0.1.5.dist-info/top_level.txt
chatmux-0.1.5.dist-info/RECORD
