Metadata-Version: 2.4
Name: chatmux
Version: 0.1.5
Summary: Convert between common LLM chat schemas
Requires-Python: >=3.10.14
License-File: LICENSE
Requires-Dist: pillow==10.4.0
Requires-Dist: pydantic>=2.11.3
Dynamic: license-file
